ankicc/__init__.py
ankicc/cc.py
ankicc/console.py
ankicc-0.3.0.dist-info/entry_points.txt
ankicc-0.3.0.dist-info/LICENSE
ankicc-0.3.0.dist-info/WHEEL
ankicc-0.3.0.dist-info/METADATA
ankicc-0.3.0.dist-info/RECORD
