Metadata-Version: 2.1
Name: ankicc
Version: 0.3.0
Summary: Convert all fields of Anki deck package (*.apkg) between traditional and simplified Chinese
Author: kaiiiz
Author-email: ukaizheng@gmail.com
Requires-Python: >=3.7,<4.0
Classifier: Programming Language :: Python :: 3
Classifier: Programming Language :: Python :: 3.10
Classifier: Programming Language :: Python :: 3.7
Classifier: Programming Language :: Python :: 3.8
Classifier: Programming Language :: Python :: 3.9
Requires-Dist: OpenCC (>=1.1.1,<2.0.0)
Requires-Dist: ankipandas (>=0.3.10,<0.4.0)
